[{"date":"Wed, 03 Dec 2014 23:20:41 GMT","sloc":69,"lloc":23,"functions":7,"deliveredBugs":0.2947294495030259,"maintainability":77.91542806360313,"lintErrors":[],"difficulty":15.044117647058824},{"date":"Thu, 04 Dec 2014 00:42:59 GMT","sloc":69,"lloc":23,"functions":7,"deliveredBugs":0.2947294495030259,"maintainability":77.91542806360313,"lintErrors":[],"difficulty":15.044117647058824},{"date":"Mon, 05 Jan 2015 17:57:22 GMT","sloc":69,"lloc":23,"functions":7,"deliveredBugs":0.2947294495030259,"maintainability":77.91542806360313,"lintErrors":[],"difficulty":15.044117647058824},{"date":"Mon, 18 May 2015 21:35:34 GMT","sloc":69,"lloc":23,"functions":7,"deliveredBugs":0.2947294495030259,"maintainability":77.91542806360313,"lintErrors":[],"difficulty":15.044117647058824}]