{"info":{"file":"JSON-js/json_parse.js","fileShort":"JSON-js/json_parse.js","fileSafe":"JSON_js_json_parse_js","link":"files/JSON_js_json_parse_js/index.html"},"complexity":{"aggregate":{"sloc":{"logical":185,"physical":299},"cyclomatic":43,"halstead":{"operators":{"distinct":34,"total":295,"identifiers":["__stripped__"]},"operands":{"distinct":99,"total":358,"identifiers":["__stripped__"]},"length":653,"vocabulary":133,"difficulty":61.47474747474748,"volume":4607.099430382277,"effort":283220.27407380345,"bugs":1.5356998101274257,"time":15734.459670766859},"params":6,"line":56,"cyclomaticDensity":23.243243243243246,"complexity":{"cyclomatic":43,"sloc":{"logical":185,"physical":299},"halstead":{"operators":{"distinct":34,"total":295,"identifiers":["__stripped__"]},"operands":{"distinct":99,"total":358,"identifiers":["__stripped__"]},"length":653,"vocabulary":133,"difficulty":61.47474747474748,"volume":4607.099430382277,"effort":283220.27407380345,"bugs":1.5356998101274257,"time":15734.459670766859}}},"functions":[{"name":"<anonymous>","sloc":{"logical":24,"physical":299},"cyclomatic":1,"halstead":{"operators":{"distinct":6,"total":31,"identifiers":["__stripped__"]},"operands":{"distinct":28,"total":42,"identifiers":["__stripped__"]},"length":73,"vocabulary":34,"difficulty":4.5,"volume":371.38478741127483,"effort":1671.2315433507367,"bugs":0.12379492913709161,"time":92.84619685281871},"params":0,"line":56,"cyclomaticDensity":4.166666666666666,"complexity":{"cyclomatic":1,"sloc":{"logical":24,"physical":299},"halstead":{"operators":{"distinct":6,"total":31,"identifiers":["__stripped__"]},"operands":{"distinct":28,"total":42,"identifiers":["__stripped__"]},"length":73,"vocabulary":34,"difficulty":4.5,"volume":371.38478741127483,"effort":1671.2315433507367,"bugs":0.12379492913709161,"time":92.84619685281871}}},{"name":"error","sloc":{"logical":5,"physical":11},"cyclomatic":1,"halstead":{"operators":{"distinct":3,"total":6,"identifiers":["__stripped__"]},"operands":{"distinct":7,"total":10,"identifiers":["__stripped__"]},"length":16,"vocabulary":10,"difficulty":2.142857142857143,"volume":53.1508495181978,"effort":113.89467753899528,"bugs":0.017716949839399268,"time":6.327482085499738},"params":1,"line":81,"cyclomaticDensity":20,"complexity":{"cyclomatic":1,"sloc":{"logical":5,"physical":11},"halstead":{"operators":{"distinct":3,"total":6,"identifiers":["__stripped__"]},"operands":{"distinct":7,"total":10,"identifiers":["__stripped__"]},"length":16,"vocabulary":10,"difficulty":2.142857142857143,"volume":53.1508495181978,"effort":113.89467753899528,"bugs":0.017716949839399268,"time":6.327482085499738}}},{"name":"next","sloc":{"logical":5,"physical":15},"cyclomatic":2,"halstead":{"operators":{"distinct":9,"total":13,"identifiers":["__stripped__"]},"operands":{"distinct":10,"total":17,"identifiers":["__stripped__"]},"length":30,"vocabulary":19,"difficulty":7.6499999999999995,"volume":127.43782540330756,"effort":974.8993643353027,"bugs":0.042479275134435855,"time":54.161075796405704},"params":1,"line":93,"cyclomaticDensity":40,"complexity":{"cyclomatic":2,"sloc":{"logical":5,"physical":15},"halstead":{"operators":{"distinct":9,"total":13,"identifiers":["__stripped__"]},"operands":{"distinct":10,"total":17,"identifiers":["__stripped__"]},"length":30,"vocabulary":19,"difficulty":7.6499999999999995,"volume":127.43782540330756,"effort":974.8993643353027,"bugs":0.042479275134435855,"time":54.161075796405704}}},{"name":"number","sloc":{"logical":26,"physical":40},"cyclomatic":11,"halstead":{"operators":{"distinct":15,"total":48,"identifiers":["__stripped__"]},"operands":{"distinct":15,"total":55,"identifiers":["__stripped__"]},"length":103,"vocabulary":30,"difficulty":27.5,"volume":505.40973134767745,"effort":13898.76761206113,"bugs":0.16846991044922582,"time":772.1537562256184},"params":0,"line":109,"cyclomaticDensity":42.30769230769231,"complexity":{"cyclomatic":11,"sloc":{"logical":26,"physical":40},"halstead":{"operators":{"distinct":15,"total":48,"identifiers":["__stripped__"]},"operands":{"distinct":15,"total":55,"identifiers":["__stripped__"]},"length":103,"vocabulary":30,"difficulty":27.5,"volume":505.40973134767745,"effort":13898.76761206113,"bugs":0.16846991044922582,"time":772.1537562256184}}},{"name":"string","sloc":{"logical":27,"physical":41},"cyclomatic":9,"halstead":{"operators":{"distinct":17,"total":45,"identifiers":["__stripped__"]},"operands":{"distinct":22,"total":49,"identifiers":["__stripped__"]},"length":94,"vocabulary":39,"difficulty":18.93181818181818,"volume":496.82780857305136,"effort":9405.853739576176,"bugs":0.16560926952435046,"time":522.5474299764542},"params":0,"line":150,"cyclomaticDensity":33.33333333333333,"complexity":{"cyclomatic":9,"sloc":{"logical":27,"physical":41},"halstead":{"operators":{"distinct":17,"total":45,"identifiers":["__stripped__"]},"operands":{"distinct":22,"total":49,"identifiers":["__stripped__"]},"length":94,"vocabulary":39,"difficulty":18.93181818181818,"volume":496.82780857305136,"effort":9405.853739576176,"bugs":0.16560926952435046,"time":522.5474299764542}}},{"name":"white","sloc":{"logical":2,"physical":8},"cyclomatic":2,"halstead":{"operators":{"distinct":4,"total":4,"identifiers":["__stripped__"]},"operands":{"distinct":3,"total":4,"identifiers":["__stripped__"]},"length":8,"vocabulary":7,"difficulty":2.6666666666666665,"volume":22.458839376460833,"effort":59.89023833722889,"bugs":0.007486279792153611,"time":3.327235463179383},"params":0,"line":192,"cyclomaticDensity":100,"complexity":{"cyclomatic":2,"sloc":{"logical":2,"physical":8},"halstead":{"operators":{"distinct":4,"total":4,"identifiers":["__stripped__"]},"operands":{"distinct":3,"total":4,"identifiers":["__stripped__"]},"length":8,"vocabulary":7,"difficulty":2.6666666666666665,"volume":22.458839376460833,"effort":59.89023833722889,"bugs":0.007486279792153611,"time":3.327235463179383}}},{"name":"word","sloc":{"logical":21,"physical":27},"cyclomatic":4,"halstead":{"operators":{"distinct":5,"total":23,"identifiers":["__stripped__"]},"operands":{"distinct":17,"total":37,"identifiers":["__stripped__"]},"length":60,"vocabulary":22,"difficulty":5.441176470588235,"volume":267.56589711823784,"effort":1455.8732637315882,"bugs":0.08918863237274595,"time":80.88184798508823},"params":0,"line":201,"cyclomaticDensity":19.047619047619047,"complexity":{"cyclomatic":4,"sloc":{"logical":21,"physical":27},"halstead":{"operators":{"distinct":5,"total":23,"identifiers":["__stripped__"]},"operands":{"distinct":17,"total":37,"identifiers":["__stripped__"]},"length":60,"vocabulary":22,"difficulty":5.441176470588235,"volume":267.56589711823784,"effort":1455.8732637315882,"bugs":0.08918863237274595,"time":80.88184798508823}}},{"name":"array","sloc":{"logical":16,"physical":26},"cyclomatic":5,"halstead":{"operators":{"distinct":9,"total":23,"identifiers":["__stripped__"]},"operands":{"distinct":12,"total":27,"identifiers":["__stripped__"]},"length":50,"vocabulary":21,"difficulty":10.125,"volume":219.61587113893805,"effort":2223.6106952817477,"bugs":0.07320529037964602,"time":123.53392751565265},"params":0,"line":231,"cyclomaticDensity":31.25,"complexity":{"cyclomatic":5,"sloc":{"logical":16,"physical":26},"halstead":{"operators":{"distinct":9,"total":23,"identifiers":["__stripped__"]},"operands":{"distinct":12,"total":27,"identifiers":["__stripped__"]},"length":50,"vocabulary":21,"difficulty":10.125,"volume":219.61587113893805,"effort":2223.6106952817477,"bugs":0.07320529037964602,"time":123.53392751565265}}},{"name":"object","sloc":{"logical":22,"physical":33},"cyclomatic":6,"halstead":{"operators":{"distinct":10,"total":34,"identifiers":["__stripped__"]},"operands":{"distinct":19,"total":42,"identifiers":["__stripped__"]},"length":76,"vocabulary":29,"difficulty":11.05263157894737,"volume":369.2065556296955,"effort":4080.7040359071616,"bugs":0.12306885187656517,"time":226.70577977262008},"params":0,"line":258,"cyclomaticDensity":27.27272727272727,"complexity":{"cyclomatic":6,"sloc":{"logical":22,"physical":33},"halstead":{"operators":{"distinct":10,"total":34,"identifiers":["__stripped__"]},"operands":{"distinct":19,"total":42,"identifiers":["__stripped__"]},"length":76,"vocabulary":29,"difficulty":11.05263157894737,"volume":369.2065556296955,"effort":4080.7040359071616,"bugs":0.12306885187656517,"time":226.70577977262008}}},{"name":"<anonymous>","sloc":{"logical":12,"physical":21},"cyclomatic":6,"halstead":{"operators":{"distinct":9,"total":22,"identifiers":["__stripped__"]},"operands":{"distinct":13,"total":16,"identifiers":["__stripped__"]},"length":38,"vocabulary":22,"difficulty":5.538461538461538,"volume":169.4584015082173,"effort":938.5388391224342,"bugs":0.05648613383607243,"time":52.14104661791301},"params":0,"line":292,"cyclomaticDensity":50,"complexity":{"cyclomatic":6,"sloc":{"logical":12,"physical":21},"halstead":{"operators":{"distinct":9,"total":22,"identifiers":["__stripped__"]},"operands":{"distinct":13,"total":16,"identifiers":["__stripped__"]},"length":38,"vocabulary":22,"difficulty":5.538461538461538,"volume":169.4584015082173,"effort":938.5388391224342,"bugs":0.05648613383607243,"time":52.14104661791301}}},{"name":"<anonymous>","sloc":{"logical":11,"physical":37},"cyclomatic":3,"halstead":{"operators":{"distinct":11,"total":17,"identifiers":["__stripped__"]},"operands":{"distinct":16,"total":23,"identifiers":["__stripped__"]},"length":40,"vocabulary":27,"difficulty":7.90625,"volume":190.19550008653877,"effort":1503.733172559197,"bugs":0.06339850002884626,"time":83.54073180884428},"params":2,"line":317,"cyclomaticDensity":27.27272727272727,"complexity":{"cyclomatic":3,"sloc":{"logical":11,"physical":37},"halstead":{"operators":{"distinct":11,"total":17,"identifiers":["__stripped__"]},"operands":{"distinct":16,"total":23,"identifiers":["__stripped__"]},"length":40,"vocabulary":27,"difficulty":7.90625,"volume":190.19550008653877,"effort":1503.733172559197,"bugs":0.06339850002884626,"time":83.54073180884428}}},{"name":"walk","sloc":{"logical":12,"physical":16},"cyclomatic":4,"halstead":{"operators":{"distinct":13,"total":25,"identifiers":["__stripped__"]},"operands":{"distinct":13,"total":34,"identifiers":["__stripped__"]},"length":59,"vocabulary":26,"difficulty":17,"volume":277.32594337032447,"effort":4714.541037295516,"bugs":0.09244198112344149,"time":261.9189465164175},"params":2,"line":336,"cyclomaticDensity":33.33333333333333,"complexity":{"cyclomatic":4,"sloc":{"logical":12,"physical":16},"halstead":{"operators":{"distinct":13,"total":25,"identifiers":["__stripped__"]},"operands":{"distinct":13,"total":34,"identifiers":["__stripped__"]},"length":59,"vocabulary":26,"difficulty":17,"volume":277.32594337032447,"effort":4714.541037295516,"bugs":0.09244198112344149,"time":261.9189465164175}}}],"dependencies":[],"maintainability":57.71102475319281,"loc":15.25,"cyclomatic":4.5,"effort":3420.128184924768,"params":0.5,"module":"JSON-js/json_parse.js"},"jshint":{"messages":[{"severity":"error","line":49,"column":1,"message":"Bad option value.","source":"Bad option value."},{"severity":"error","line":309,"column":17,"message":"Bad line breaking before '?'.","source":"Bad line breaking before '{a}'."},{"severity":"error","line":336,"column":13,"message":"Bad line breaking before '?'.","source":"Bad line breaking before '{a}'."}]}}